superqt/__init__.py
superqt/py.typed
superqt/cmap/__init__.py
superqt/cmap/_catalog_combo.py
superqt/cmap/_cmap_combo.py
superqt/cmap/_cmap_item_delegate.py
superqt/cmap/_cmap_line_edit.py
superqt/cmap/_cmap_utils.py
superqt/collapsible/__init__.py
superqt/collapsible/_collapsible.py
superqt/combobox/__init__.py
superqt/combobox/_color_combobox.py
superqt/combobox/_enum_combobox.py
superqt/combobox/_searchable_combo_box.py
superqt/elidable/__init__.py
superqt/elidable/_eliding.py
superqt/elidable/_eliding_label.py
superqt/elidable/_eliding_line_edit.py
superqt/fonticon/__init__.py
superqt/fonticon/_animations.py
superqt/fonticon/_iconfont.py
superqt/fonticon/_plugins.py
superqt/fonticon/_qfont_icon.py
superqt/iconify/__init__.py
superqt/qtcompat/__init__.py
superqt/selection/__init__.py
superqt/selection/_searchable_list_widget.py
superqt/selection/_searchable_tree_widget.py
superqt/sliders/__init__.py
superqt/sliders/_generic_range_slider.py
superqt/sliders/_generic_slider.py
superqt/sliders/_labeled.py
superqt/sliders/_range_style.py
superqt/sliders/_sliders.py
superqt/spinbox/__init__.py
superqt/spinbox/_intspin.py
superqt/spinbox/_quantity.py
superqt/switch/__init__.py
superqt/switch/_toggle_switch.py
superqt/utils/__init__.py
superqt/utils/_code_syntax_highlight.py
superqt/utils/_ensure_thread.py
superqt/utils/_errormsg_context.py
superqt/utils/_flow_layout.py
superqt/utils/_img_utils.py
superqt/utils/_message_handler.py
superqt/utils/_misc.py
superqt/utils/_qthreading.py
superqt/utils/_throttler.py
superqt/utils/_util.py
superqt-0.7.5.dist-info/METADATA
superqt-0.7.5.dist-info/WHEEL
superqt-0.7.5.dist-info/licenses/LICENSE
superqt-0.7.5.dist-info/RECORD
